{
  "videos": [
    {
      "id": "video1",
      "title": "Elle Marz — Just the Tip Tease",
      "description": "Suggestive tease clip featuring Elle Marz",
      "thumbnail": "assets/images/thumb1.webp",
      "embedUrl": "https://coomer.st/onlyfans/user/ellemarz/post/1934594411",
      "duration": "N/A",
      "category": "trending",
      "tags": ["ellemarz", "tease"],
      "uploadDate": "2025-09-20"
    },
    {
      "id": "video2",
      "title": "bubblexgun — Couldn’t Hold Back 😳",
      "description": "Playful but intense session from bubblexgun",
      "thumbnail": "assets/images/thumb2.webp",
      "embedUrl": "https://coomer.st/fansly/user/344647382891245568/post/824135203839553536",
      "duration": "N/A",
      "category": "popular",
      "tags": ["bubblexgun", "intense"],
      "uploadDate": "2025-09-20"
    },
    {
      "id": "video3",
      "title": "alexbreecooper — Pushed to My Limits 🔥",
      "description": "Boundary-pushing content from alexbreecooper",
      "thumbnail": "assets/images/thumb3.webp",
      "embedUrl": "https://coomer.st/fansly/user/285282599713124352/post/824657406456778753",
      "duration": "N/A",
      "category": "extreme",
      "tags": ["alexbreecooper", "hardcore"],
      "uploadDate": "2025-09-20"
    },
    {
      "id": "video4",
      "title": "Rose Beck — Too Worked Up to Wait 😏",
      "description": "Rose Beck gets started before the fun even begins",
      "thumbnail": "assets/images/thumb4.webp",
      "embedUrl": "https://coomer.st/onlyfans/user/rosebeck/post/1970018337",
      "duration": "N/A",
      "category": "popular",
      "tags": ["rosebeck", "teasing"],
      "uploadDate": "2025-09-20"
    },
    {
      "id": "video5",
      "title": "Chloee Mae — A Night to Remember 💦",
      "description": "Chloee Mae’s long, wild night from start to finish",
      "thumbnail": "assets/images/thumb5.webp",
      "embedUrl": "https://coomer.st/onlyfans/user/chloeemae/post/1953759853",
      "duration": "N/A",
      "category": "featured",
      "tags": ["chloeemae", "party"],
      "uploadDate": "2025-09-20"
    },
    {
      "id": "video6",
      "title": "sexyflowerwater — Breaktime Fun 👀",
      "description": "Quick solo play session with creative angles",
      "thumbnail": "assets/images/thumb6.webp",
      "embedUrl": "https://coomer.st/fansly/user/347519227445391361/post/824029853127819264",
      "duration": "N/A",
      "category": "solo",
      "tags": ["sexyflowerwater", "solo"],
      "uploadDate": "2025-09-20"
    }
  ],
  "affiliateOptions": [
    {
      "id": "instabang",
      "title": "Verify with Instabang",
      "subtitle": "Quick verification process",
      "type": "dating",
      "color": "blue",
      "url": "https://t.mbsrv2.com/388143/5380?aff_sub5=SF_006OG000004lmDN",
      "geo": "8 countries",
      "flow": "SOI",
      "priority": 1
    },
    {
      "id": "bootycallz",
      "title": "Verify with BootyCallz",
      "subtitle": "Fast verification method",
      "type": "dating",
      "color": "green",
      "url": "https://t.mbsrv2.com/388143/7411?bo=2753,2754,2755,2756&popUnder=true&aff_sub5=SF_006OG000004lmDN",
      "geo": "8 countries",
      "flow": "SOI",
      "priority": 2
    }
  ]
}
